bspider/VERSION
bspider/__init__.py
bspider/cmdline.py
bspider/agent/__init__.py
bspider/agent/server.py
bspider/agent/controller/__init__.py
bspider/agent/controller/code.py
bspider/agent/controller/data_source.py
bspider/agent/controller/node.py
bspider/agent/controller/project.py
bspider/agent/controller/validators/__init__.py
bspider/agent/controller/validators/code_form.py
bspider/agent/controller/validators/data_source_form.py
bspider/agent/controller/validators/project_form.py
bspider/agent/controller/validators/worker_forms.py
bspider/agent/service/__init__.py
bspider/agent/service/code.py
bspider/agent/service/data_source.py
bspider/agent/service/node.py
bspider/agent/service/project.py
bspider/bcron/__init__.py
bspider/bcron/base_operation.py
bspider/bcron/job.py
bspider/bcron/jobstore.py
bspider/bcron/scheduler.py
bspider/bcron/todo.py
bspider/bcron/work.py
bspider/commands/__init__.py
bspider/commands/agent.py
bspider/commands/master.py
bspider/commands/mkmdw.py
bspider/commands/mkpipe.py
bspider/commands/mkplatform.py
bspider/commands/mkspider.py
bspider/commands/rmplatform.py
bspider/commands/version.py
bspider/config/__init__.py
bspider/config/default_settings.py
bspider/config/rbac_model.conf
bspider/config/rbac_policy.csv
bspider/core/__init__.py
bspider/core/agent_cache.py
bspider/core/base_manager.py
bspider/core/base_monitor.py
bspider/core/broker.py
bspider/core/custom_module.py
bspider/core/project.py
bspider/core/api/__init__.py
bspider/core/api/api_response.py
bspider/core/api/base_form.py
bspider/core/api/base_impl.py
bspider/core/api/base_service.py
bspider/core/api/exception.py
bspider/core/api/remote_mixin.py
bspider/core/api/auth/__init__.py
bspider/core/api/auth/token.py
bspider/debug/__init__.py
bspider/debug/debuger.py
bspider/downloader/__init__.py
bspider/downloader/async_downloader.py
bspider/downloader/base_middleware.py
bspider/downloader/downloader_monitor.py
bspider/downloader/work.py
bspider/http/__init__.py
bspider-0.0.8.dist-info/METADATA
bspider-0.0.8.dist-info/WHEEL
bspider-0.0.8.dist-info/entry_points.txt
bspider-0.0.8.dist-info/top_level.txt
bspider-0.0.8.dist-info/RECORD
