Metadata-Version: 2.1
Name: bspider
Version: 0.0.8
Summary: A high-level distributed crawling framework Git: https://github.com/littlebai3618/bspider
Home-page: UNKNOWN
Author: baii
Author-email: 2624386844@qq.com
License: BSD
Platform: UNKNOWN
Classifier: Framework :: Scrapy
Classifier: Development Status :: 5 - Production/Stable
Classifier: Environment :: Console
Classifier: Intended Audience :: Developers
Classifier: License :: OSI Approved :: BSD License
Classifier: Operating System :: OS Independent
Classifier: Programming Language :: Python :: 3.7
Classifier: Programming Language :: Python :: Implementation :: CPython
Classifier: Topic :: Internet :: WWW/HTTP
Classifier: Topic :: Software Development :: Libraries :: Application Frameworks
Classifier: Topic :: Software Development :: Libraries :: Python Modules
Requires-Python: >=3.7, !=3.0.*, !=3.1.*, !=3.2.*, !=3.3.*, !=3.4.*
Requires-Dist: aiohttp (==3.6.2)
Requires-Dist: aiomysql (==0.0.20)
Requires-Dist: aiormq (==2.7.2)
Requires-Dist: APScheduler (==3.6.1)
Requires-Dist: asn1crypto (==0.24.0)
Requires-Dist: async-timeout (==3.0.1)
Requires-Dist: attrs (==19.1.0)
Requires-Dist: casbin (==0.7.1)
Requires-Dist: certifi (==2019.6.16)
Requires-Dist: cffi (==1.12.3)
Requires-Dist: chardet (==3.0.4)
Requires-Dist: Click (==7.0)
Requires-Dist: cryptography (==2.7)
Requires-Dist: DBUtils (==1.3)
Requires-Dist: Flask (==1.1.1)
Requires-Dist: Flask-Cors (==3.0.8)
Requires-Dist: Flask-HTTPAuth (==3.3.0)
Requires-Dist: Flask-WTF (==0.14.2)
Requires-Dist: gevent (==1.4.0)
Requires-Dist: greenlet (==0.4.15)
Requires-Dist: gunicorn (==19.9.0)
Requires-Dist: idna (==2.8)
Requires-Dist: itsdangerous (==1.1.0)
Requires-Dist: Jinja2 (==2.10.1)
Requires-Dist: lxml (==4.4.1)
Requires-Dist: MarkupSafe (==1.1.1)
Requires-Dist: meld3 (==1.0.2)
Requires-Dist: multidict (==4.5.2)
Requires-Dist: pamqp (==2.3.0)
Requires-Dist: pika (==1.1.0)
Requires-Dist: psutil (>=5.6.6)
Requires-Dist: pycparser (==2.19)
Requires-Dist: PyMySQL (==0.9.2)
Requires-Dist: pytz (==2019.2)
Requires-Dist: requests (==2.22.0)
Requires-Dist: simpleeval (==0.9.8)
Requires-Dist: six (==1.12.0)
Requires-Dist: supervisor (==4.0.4)
Requires-Dist: tzlocal (==2.0.0)
Requires-Dist: urllib3 (==1.25.3)
Requires-Dist: Werkzeug (==0.15.5)
Requires-Dist: WTForms (==2.2.1)
Requires-Dist: xpinyin (==0.5.6)
Requires-Dist: yarl (==1.3.0)
Requires-Dist: redis (==3.3.11)
Requires-Dist: PyYAML (==5.2)
Requires-Dist: voluptuous (==0.11.7)
